rwanda_locations_api/__init__.py
rwanda_locations_api/main.py
rwanda_locations_api/locs/__init__.py
rwanda_locations_api/locs/data.py
rwanda_locations_api/locs/lookup.py
rwanda_locations_api/locs/locs/__init__.py
rwanda_locations_api/locs/locs/locations.json
rwanda_locations_api-0.1.1.dist-info/METADATA
rwanda_locations_api-0.1.1.dist-info/WHEEL
rwanda_locations_api-0.1.1.dist-info/top_level.txt
rwanda_locations_api-0.1.1.dist-info/RECORD
