Metadata-Version: 2.4
Name: rwanda-locations-api
Version: 0.1.1
Summary: API package containing all regions of Rwanda from provinces to villages.
Author: MWIMULE Bienvenu
Author-email: mwimulebienvenu05@gmail.com
Classifier: Programming Language :: Python :: 3
Classifier: Operating System :: OS Independent
Requires-Python: >=3.7
Dynamic: author
Dynamic: author-email
Dynamic: classifier
Dynamic: description
Dynamic: description-content-type
Dynamic: requires-python
Dynamic: summary
